py_mortgage/__init__.py
py_mortgage/mortgage.py
py_mortgage/tests.py
py_mortgage-0.2.3.dist-info/LICENSE
py_mortgage-0.2.3.dist-info/METADATA
py_mortgage-0.2.3.dist-info/WHEEL
py_mortgage-0.2.3.dist-info/top_level.txt
py_mortgage-0.2.3.dist-info/RECORD
