Metadata-Version: 2.1
Name: py-mortgage
Version: 0.2.3
Summary: A package to handle mortgage calculations
Home-page: https://github.com/tdsprogramming/py-mortgage
Author: tdsprogramming
License: UNKNOWN
Platform: UNKNOWN
Classifier: Programming Language :: Python :: 3
Classifier: License :: OSI Approved :: MIT License
Classifier: Operating System :: OS Independent
Requires-Dist: pandas (>=0.25.3)
